{
  "attributes": [
    {
      "default": "nil",
      "size": null,
      "type": "uuid",
      "source": "id",
      "references": null,
      "allow_nil?": false,
      "primary_key?": true,
      "generated?": false
    },
    {
      "default": "nil",
      "size": null,
      "type": "text",
      "source": "endpoint",
      "references": null,
      "allow_nil?": false,
      "primary_key?": false,
      "generated?": false
    },
    {
      "default": "nil",
      "size": null,
      "type": "text",
      "source": "model",
      "references": null,
      "allow_nil?": false,
      "primary_key?": false,
      "generated?": false
    },
    {
      "default": "nil",
      "size": null,
      "type": "text",
      "source": "api_key",
      "references": null,
      "allow_nil?": true,
      "primary_key?": false,
      "generated?": false
    },
    {
      "default": "nil",
      "size": null,
      "type": "utc_datetime_usec",
      "source": "inserted_at",
      "references": null,
      "allow_nil?": false,
      "primary_key?": false,
      "generated?": false
    },
    {
      "default": "nil",
      "size": null,
      "type": "utc_datetime_usec",
      "source": "updated_at",
      "references": null,
      "allow_nil?": false,
      "primary_key?": false,
      "generated?": false
    },
    {
      "default": "nil",
      "size": null,
      "type": "uuid",
      "source": "user_id",
      "references": {
        "name": "speech_settings_user_id_fkey",
        "table": "users",
        "multitenancy": {
          "global": null,
          "strategy": null,
          "attribute": null
        },
        "on_delete": "delete",
        "primary_key?": true,
        "destination_attribute": "id",
        "on_update": null,
        "deferrable": false,
        "destination_attribute_default": null,
        "destination_attribute_generated": null
      },
      "allow_nil?": true,
      "primary_key?": false,
      "generated?": false
    }
  ],
  "table": "speech_settings",
  "hash": "D60212CADD26298035024FE1C49DEA1C76C3A394732898F4354A35505DC31338",
  "multitenancy": {
    "global": null,
    "strategy": null,
    "attribute": null
  },
  "identities": [],
  "repo": "Elixir.Dala.Repo",
  "strict?": false,
  "custom_indexes": [],
  "base_filter": null,
  "custom_statements": [],
  "has_create_action": true
}